loggerV/__init__.py
loggerV/logger.py
loggerv-1.0.2.dist-info/METADATA
loggerv-1.0.2.dist-info/WHEEL
loggerv-1.0.2.dist-info/licenses/LICENSE
loggerv-1.0.2.dist-info/RECORD
