Metadata-Version: 2.1
Name: loggerV
Version: 1.0.2
Summary: A logger class, and a decorator that works with that class for python
Project-URL: Homepage, https://github.com/aaronv15/logger_v-python
Project-URL: Bug Tracker, https://github.com/aaronv15/logger_v-python/issues
Author-email: Aharon Vegoda <aaronvegoda@gmail.com>
Maintainer-email: Aharon Vegoda <aaronvegoda@gmail.com>
License-File: LICENSE
Classifier: License :: OSI Approved :: MIT License
Classifier: Operating System :: OS Independent
Classifier: Programming Language :: Python :: 3
Requires-Python: >=3.7
